backendservice/__init__.py
backendservice/grpc/__init__.py
backendservice/grpc/grpc_service_api.py
backendservice/grpc/grpcutils.py
backendservice/grpc/sys/__init__.py
backendservice/grpc/sys/grpc_sys_model_utils.py
backendservice/grpc/sys/sys_service_api.py
backendservice/grpc/sys/sysservice_pb2.py
backendservice/grpc/sys/sysservice_pb2.pyi
backendservice/grpc/sys/sysservice_pb2_grpc.py
backendservice/grpc/tasks/__init__.py
backendservice/grpc/tasks/data_service_api.py
backendservice/grpc/tasks/dataservice_pb2.py
backendservice/grpc/tasks/dataservice_pb2.pyi
backendservice/grpc/tasks/dataservice_pb2_grpc.py
backendservice/grpc/tasks/grpc_model_utils.py
backendservice/grpc/tasks/grpc_models.py
backendservice/services/__init__.py
backendservice/util/__init__.py
backendservice/util/exceptions.py
backendservice/util/jsonencoder.py
backendservice/util/syncutils.py
backendservice/util/utils.py
data_service_api_p12-1.0.17.dist-info/METADATA
data_service_api_p12-1.0.17.dist-info/WHEEL
data_service_api_p12-1.0.17.dist-info/top_level.txt
data_service_api_p12-1.0.17.dist-info/RECORD
